fastapi_startup/__init__.py
fastapi_startup/main.py
fastapi_startup-0.2.1.dist-info/LICENSE
fastapi_startup-0.2.1.dist-info/WHEEL
fastapi_startup-0.2.1.dist-info/METADATA
fastapi_startup-0.2.1.dist-info/RECORD
