Metadata-Version: 2.1
Name: fastapi-startup
Version: 0.2.1
Summary: An opinionated startup extension for FastAPI.
Author-email: Håvard Vidme <havard.vidme@kartverket.no>
Requires-Python: >=3.6.1
Classifier: Development Status :: 4 - Beta
Classifier: Framework :: FastAPI
Classifier: Intended Audience :: Developers
Classifier: License :: OSI Approved :: MIT License
Classifier: Programming Language :: Python :: 3 :: Only
Classifier: Programming Language :: Python :: 3.7
Classifier: Programming Language :: Python :: 3.8
Classifier: Programming Language :: Python :: 3.9
Classifier: Programming Language :: Python :: 3.10
Classifier: Topic :: Internet :: WWW/HTTP
Classifier: Topic :: Internet :: WWW/HTTP :: HTTP Servers
Requires-Dist: fastapi >=0.65.2
Requires-Dist: black ; extra == "dev"
Requires-Dist: isort ; extra == "dev"
Requires-Dist: pytest ; extra == "test"
Requires-Dist: requests ; extra == "test"
Project-URL: Home, https://github.com/vidhav/fastapi-startup
Provides-Extra: dev
Provides-Extra: test
